btrfs2s3/__init__.py
btrfs2s3/py.typed
btrfs2s3/_internal/__init__.py
btrfs2s3/_internal/arrowutil.py
btrfs2s3/_internal/backups.py
btrfs2s3/_internal/btrfsioctl.py
btrfs2s3/_internal/config.py
btrfs2s3/_internal/console.py
btrfs2s3/_internal/cvar.py
btrfs2s3/_internal/main.py
btrfs2s3/_internal/piper.py
btrfs2s3/_internal/planner.py
btrfs2s3/_internal/preservation.py
btrfs2s3/_internal/resolver.py
btrfs2s3/_internal/s3.py
btrfs2s3/_internal/stream_uploader.py
btrfs2s3/_internal/time_span_describer.py
btrfs2s3/_internal/util.py
btrfs2s3/_internal/commands/__init__.py
btrfs2s3/_internal/commands/update2.py
btrfs2s3-2.1.0.dist-info/LICENSE
btrfs2s3-2.1.0.dist-info/METADATA
btrfs2s3-2.1.0.dist-info/WHEEL
btrfs2s3-2.1.0.dist-info/entry_points.txt
btrfs2s3-2.1.0.dist-info/top_level.txt
btrfs2s3-2.1.0.dist-info/RECORD
