Metadata-Version: 2.2
Name: btrfs2s3
Version: 2.1.0
Summary: Snapshot btrfs volumes and back them up to s3
Author-email: Steven Brudenell <steven.brudenell@gmail.com>
Project-URL: homepage, https://github.com/sbrudenell/btrfs2s3
Classifier: Programming Language :: Python :: 3 :: Only
Classifier: Programming Language :: Python :: 3.9
Classifier: Programming Language :: Python :: 3.10
Classifier: Programming Language :: Python :: 3.11
Classifier: Programming Language :: Python :: 3.12
Classifier: Programming Language :: Python :: 3.13
Requires-Python: >=3.9
License-File: LICENSE
Requires-Dist: arrow<2,>=1
Requires-Dist: boto3[crt]<2,>=1
Requires-Dist: cfgv<4,>=3
Requires-Dist: pyyaml<7,>=6
Requires-Dist: rich<14,>=13
Requires-Dist: typing-extensions<5,>=4.4
Requires-Dist: tzdata
